tadr-2.0.1.6.data/scripts/tadr
tadrcore/__init__.py
tadrcore/auth.py
tadrcore/creds.py
tadrcore/globals.py
tadrcore/logger.py
tadrcore/main.py
tadrcore/misc.py
tadr-2.0.1.6.dist-info/LICENSE
tadr-2.0.1.6.dist-info/METADATA
tadr-2.0.1.6.dist-info/WHEEL
tadr-2.0.1.6.dist-info/top_level.txt
tadr-2.0.1.6.dist-info/RECORD
