Metadata-Version: 2.1
Name: tadr
Version: 2.0.1.6
Summary: A tool that will automatically reply done to the first 'cannot find transcription' message from the r/TranscribersOfReddit bot.
Home-page: https://github.com/MurdoMaclachlan/tadr
Author: Murdo Maclachlan
Author-email: murdo@maclachlans.org.uk
License: GPLv3+
Platform: UNKNOWN
Classifier: Programming Language :: Python :: 3
Classifier: License :: OSI Approved :: GNU General Public License v3 or later (GPLv3+)
Classifier: Operating System :: OS Independent
License-File: LICENSE
Requires-Dist: configparser
Requires-Dist: praw (>=7.5.0)
Requires-Dist: PyGObject (~=3.42.0)
Requires-Dist: setuptools (>=57.0.0)
